iaajon/__init__.py
iaajon-0.1.3.dist-info/DESCRIPTION.rst
iaajon-0.1.3.dist-info/METADATA
iaajon-0.1.3.dist-info/RECORD
iaajon-0.1.3.dist-info/WHEEL
iaajon-0.1.3.dist-info/metadata.json
iaajon-0.1.3.dist-info/top_level.txt
