Metadata-Version: 2.0
Name: iaajon
Version: 0.1.3
Summary: Detects potential corrupt entries in a dataframe.
Home-page: https://github.com/lionely/iaa
Author: Jonathan Scott
Author-email: lionelscotty95@gmail.com
License: BSD
Platform: UNKNOWN
Requires-Dist: googlemaps
Requires-Dist: numpy
Requires-Dist: pandas
